[
    {"name": "Ace", "category": ["Values"], "requires": "|Ace|"},
    {"name": "Two", "category": ["Values"], "requires": "|Two|"},
    {"name": "Three", "category": ["Values"], "requires": "|Three|"},
    {"name": "Four", "category": ["Values"], "requires": "|Four|"},
    {"name": "Five", "category": ["Values"], "requires": "|Five|"},
    {"name": "Six", "category": ["Values"], "requires": "|Six|"},
    {"name": "Seven", "category": ["Values"], "requires": "|Seven|"},
    {"name": "Eight", "category": ["Values"], "requires": "|Eight|"},
    {"name": "Nine", "category": ["Values"], "requires": "|Nine|"},
    {"name": "Ten", "category": ["Values"], "requires": "|Ten|"},
    {"name": "Jack", "category": ["Values"], "requires": "|Jack|"},
    {"name": "Queen", "category": ["Values"], "requires": "|Queen|"},
    {"name": "King", "category": ["Values"], "requires": "|King|"},
    {"name": "Win 1 Game", "category": ["Games", "G1"]},
    {"name": "Win 2 Games", "category": ["Games", "G2"]},
    {"name": "Win 3 Games", "category": ["Games", "G3"]},
    {"name": "Win 4 Games", "category": ["Games", "G4"]},
    {"name": "Win 5 Games", "category": ["Games", "G5"]},
    {"name": "Win the Turtle Shell Trinket", "category": ["Turtle Shell Trinket"], "place_item": "Go Fish!"},
    {"name": "Match All Card Values", "category": ["((~Goal~))"], "place_item": "Victory", "requires": "|Ace| and |Two| and |Three| and |Four| and |Five| and |Six| and |Seven| and |Eight| and |Nine| and |Ten| and |Jack| and |Queen| and |King|"}
  ]